hexicapi/__init__.py
hexicapi/client.py
hexicapi/redlogger.py
hexicapi/server.py
hexicapi/web.py
hexicapi/authpage/login.html
hexicapi/authpage/register.html
hexicapi/authpage/css/main.css
hexicapi/authpage/css/util.css
hexicapi/authpage/fonts/font-awesome-4.7.0/css/font-awesome.css
hexicapi/authpage/fonts/font-awesome-4.7.0/css/font-awesome.min.css
hexicapi/authpage/fonts/font-awesome-4.7.0/fonts/FontAwesome.otf
hexicapi/authpage/fonts/font-awesome-4.7.0/fonts/fontawesome-webfont.eot
hexicapi/authpage/fonts/font-awesome-4.7.0/fonts/fontawesome-webfont.svg
hexicapi/authpage/fonts/font-awesome-4.7.0/fonts/fontawesome-webfont.ttf
hexicapi/authpage/fonts/font-awesome-4.7.0/fonts/fontawesome-webfont.woff
hexicapi/authpage/fonts/font-awesome-4.7.0/fonts/fontawesome-webfont.woff2
hexicapi/authpage/fonts/font-awesome-4.7.0/less/animated.less
hexicapi/authpage/fonts/font-awesome-4.7.0/less/bordered-pulled.less
hexicapi/authpage/fonts/font-awesome-4.7.0/less/core.less
hexicapi/authpage/fonts/font-awesome-4.7.0/less/fixed-width.less
hexicapi/authpage/fonts/font-awesome-4.7.0/less/font-awesome.less
hexicapi/authpage/fonts/font-awesome-4.7.0/less/icons.less
hexicapi/authpage/fonts/font-awesome-4.7.0/less/larger.less
hexicapi/authpage/fonts/font-awesome-4.7.0/less/list.less
hexicapi/authpage/fonts/font-awesome-4.7.0/less/mixins.less
hexicapi/authpage/fonts/font-awesome-4.7.0/less/path.less
hexicapi/authpage/fonts/font-awesome-4.7.0/less/rotated-flipped.less
hexicapi/authpage/fonts/font-awesome-4.7.0/less/screen-reader.less
hexicapi/authpage/fonts/font-awesome-4.7.0/less/stacked.less
hexicapi/authpage/fonts/font-awesome-4.7.0/less/variables.less
hexicapi/authpage/fonts/font-awesome-4.7.0/scss/_animated.scss
hexicapi/authpage/fonts/font-awesome-4.7.0/scss/_bordered-pulled.scss
hexicapi/authpage/fonts/font-awesome-4.7.0/scss/_core.scss
hexicapi/authpage/fonts/font-awesome-4.7.0/scss/_fixed-width.scss
hexicapi/authpage/fonts/font-awesome-4.7.0/scss/_icons.scss
hexicapi-1.0.5.dist-info/METADATA
hexicapi-1.0.5.dist-info/WHEEL
hexicapi-1.0.5.dist-info/top_level.txt
hexicapi-1.0.5.dist-info/RECORD
